Profiling_damen_tools/__init__.py
Profiling_damen_tools/dataprofile.py
profiling_damen_tools-0.0.4.dist-info/METADATA
profiling_damen_tools-0.0.4.dist-info/WHEEL
profiling_damen_tools-0.0.4.dist-info/top_level.txt
profiling_damen_tools-0.0.4.dist-info/RECORD
