Metadata-Version: 2.4
Name: Profiling_damen_tools
Version: 0.0.4
Summary: Damen-library
Author-email: giandaeky <giandaekyoga10@gmail.com>
License: MIT
Project-URL: Homepage, https://pypi.org/project/Profiling_damen_tools/
Requires-Python: >=3.8
